adafruit_circuitpython_hid-6.1.8.dist-info/licenses/LICENSE
adafruit_hid/__init__.py
adafruit_hid/consumer_control.py
adafruit_hid/consumer_control_code.py
adafruit_hid/keyboard.py
adafruit_hid/keyboard_layout_base.py
adafruit_hid/keyboard_layout_us.py
adafruit_hid/keycode.py
adafruit_hid/mouse.py
adafruit_circuitpython_hid-6.1.8.dist-info/METADATA
adafruit_circuitpython_hid-6.1.8.dist-info/WHEEL
adafruit_circuitpython_hid-6.1.8.dist-info/top_level.txt
adafruit_circuitpython_hid-6.1.8.dist-info/RECORD
